verfishd/__init__.py
verfishd/core/__init__.py
verfishd/core/migration_speed.py
verfishd/core/model.py
verfishd/core/physical_factor.py
verfishd/core/physical_stimuli_profile.py
verfishd-0.2.4.dist-info/LICENSE
verfishd-0.2.4.dist-info/METADATA
verfishd-0.2.4.dist-info/WHEEL
verfishd-0.2.4.dist-info/RECORD
