Metadata-Version: 2.3
Name: verfishd
Version: 0.2.4
Summary: Simulate the vertical fish distribution influenced by physical stimuli
License: MSC
Keywords: vertical fish distribution,data-science,simulation,modelling
Author: Jan Meischner
Author-email: jan.meischner@googlemail.com
Requires-Python: >=3.11,<4.0
Classifier: Intended Audience :: Education
Classifier: Intended Audience :: Science/Research
Classifier: Programming Language :: Python
Classifier: Topic :: Scientific/Engineering :: Oceanography
Classifier: Typing :: Typed
Requires-Dist: matplotlib (>=3.10.0,<4.0.0)
Requires-Dist: numpy (>=2.2.2,<3.0.0)
Requires-Dist: pandas (>=2.2.3,<3.0.0)
Requires-Dist: rich (>=13.9.4,<14.0.0)
Requires-Dist: seabird (>=0.12.0,<0.13.0)
Requires-Dist: setuptools (>=78.1.1,<79.0.0)
Project-URL: Repository, https://github.com/marine-data-science/verfishd
